aipkgs_firebase/__init__.py
aipkgs_firebase/actions/core.py
aipkgs_firebase/helpers.py
aipkgs_firebase/messaging/core.py
aipkgs_firebase/messaging/enums.py
aipkgs_firebase/messaging/helpers.py
aipkgs_firebase/storage/core.py
aipkgs_firebase/storage/helpers.py
aipkgs_firebase/storage/root.py
aipkgs_firebase/user/core.py
aipkgs_firebase-1.0.26.dist-info/LICENSE.md
aipkgs_firebase-1.0.26.dist-info/METADATA
aipkgs_firebase-1.0.26.dist-info/WHEEL
aipkgs_firebase-1.0.26.dist-info/RECORD
