Metadata-Version: 2.1
Name: aipkgs-firebase
Version: 1.0.26
Summary: A utility package for interacting with Firebase, specifically Firestore, in a more streamlined and efficient manner.
Home-page: https://gitlab.com/aipy/public/packages.git
License: MIT
Keywords: ai
Author: Alexy
Author-email: alexy.ib@outlook.com
Requires-Python: >=3.11.4,<4.0.0
Classifier: License :: OSI Approved :: MIT License
Classifier: Programming Language :: Python :: 3
Classifier: Programming Language :: Python :: 3.12
Requires-Dist: aipkgs-core (>=1.0.0,<2.0.0)
Requires-Dist: firebase-admin (>=6.5.0,<7.0.0)
Project-URL: Repository, https://gitlab.com/aipy/public/packages.git
